Workbook

Sheet FEES AND ASSUMPTIONS
A1: CPO | C1: Charger Type | D1: kWh per Month (AC) | E1: kWh per Month (DC) | F1: # Charging Points (AC) | G1: # Charging Points (DC) | H1: Rate (AC) | I1: Rate (DC) | J1: Electricity Cost | K1: Rent / Share (AC) | L1: Rent / Share (DC) | M1: NET REVENUE (AC) | N1: NET REVENUE (DC) | O1: Rent / Share (AC) TOTAL | P1: Rent / Share (DC) TOTAL | Q1: Service Access Fee | R1: Remarks
A2: InHub EVOxCharge Charging Station | B2: CPO | C2: AC & DC | D2: 1500 | E2: 2000 | F2: 4 | G2: 6 | H2: 24 | I2: 30 | J2: 11.82 | R2: Rate based on the previous Billing
A3: REACH (current) | B3: CPO | C3: AC & DC | D3: 200 | E3: 1600 | F3: 1 | G3: 1 | H3: 26 | I3: 26 | J3: 13.14 | O3: 20160 | Q3: 37500 | R3: Rate based on the previous Billing / 2000 per car for sisters company
A4: 6NEO (N-Lima) | B4: CPO | C4: AC | D4: 600 | F4: 2 | H4: 20 | J4: 7.09 | R4: Rate based on the previous Billing
A5: PPT | B5: CPO | C5: DC | E5: 300 | G5: 2 | I5: 26 | J5: 10 | R5: Rate based on the previous Billing
A6: SM MOA Square | B6: CPO | C6: AC | D6: 1000 | F6: 3 | H6: 25 | J6: 10 | O6: =F6*6000 -> 18000
A7: SM Lucena | B7: CPO | C7: AC | D7: 700 | F7: 2 | H7: 25 | J7: 10 | O7: =F7*3000 -> 6000
A8: SM Rosales | B8: CPO | C8: AC | D8: 350 | F8: 1 | H8: 25 | J8: 10 | O8: =F8*3000 -> 3000
A9: Escala | B9: CPO | C9: AC | D9: 70 | F9: 2 | H9: 37 | J9: 10 | K9: 12
A10: ADB | B10: CPO | C10: AC | D10: 100 | F10: 15 | H10: 25.26 | J10: 10.26
A11: SM Sucat | B11: CPO | C11: AC | D11: 700 | F11: 2 | H11: 25 | J11: 10 | O11: =F11*6000 -> 12000
A12: World Trade Center | B12: CPO | C12: AC | D12: 100 | F12: 2 | H12: 30 | J12: 10
A13: S Maison at Conrad | B13: CPO | C13: AC | D13: 700 | F13: 2 | H13: 25 | J13: 10 | O13: 12000
A14: SM Sangandaan | B14: CPO | C14: AC | D14: 700 | F14: 2 | H14: 25 | J14: 10 | O14: 12000
A15: SM Grand Central | B15: CPO | C15: AC | D15: 700 | F15: 2 | H15: 25 | J15: 10 | O15: 12000
A16: SM Valenzuela | B16: CPO | C16: AC | D16: 700 | F16: 2 | H16: 25 | J16: 10 | O16: 12000
A21: CPO - JV
A22: S&R Libis | B22: CPO - JV | C22: AC & DC | D22: 200 | E22: 450 | F22: 2 | G22: 2 | H22: 25 | I22: 32 | J22: 10 | K22: 7.5 | L22: 8.8 | M22: =H22-J22-K22 -> 7.5 | N22: =I22-J22-L22 -> 13.2 | O22: =D22*F22*K22 -> 3000 | P22: =E22*G22*L22 -> 7920
A23: S&R Congressional | B23: CPO - JV | C23: AC & DC | D23: 200 | E23: 450 | F23: 2 | G23: 2 | H23: 25 | I23: 32 | J23: 10 | K23: 7.5 | L23: 8.8 | M23: =H23-J23-K23 -> 7.5 | N23: =I23-J23-L23 -> 13.2 | O23: =D23*F23*K23 -> 3000 | P23: =E23*G23*L23 -> 7920
A24: S&R New Manila | B24: CPO - JV | C24: AC & DC | D24: 200 | E24: 450 | F24: 2 | G24: 2 | H24: 25 | I24: 32 | J24: 10 | K24: 7.5 | L24: 8.8 | M24: =H24-J24-K24 -> 7.5 | N24: =I24-J24-L24 -> 13.2 | O24: =D24*F24*K24 -> 3000 | P24: =E24*G24*L24 -> 7920
A25: S&R Nuvali | B25: CPO - JV | C25: AC & DC | D25: 200 | E25: 450 | F25: 2 | G25: 2 | H25: 25 | I25: 32 | J25: 10 | K25: 7.5 | L25: 8.8 | M25: =H25-J25-K25 -> 7.5 | N25: =I25-J25-L25 -> 13.2 | O25: =D25*F25*K25 -> 3000 | P25: =E25*G25*L25 -> 7920 | R25: 24/kWh if their kWh would exceed 200kWh
A26: S&R

Sheet ACTUAL OPEX (JAN-JUN)
B1: Actual Electricity Cost | H1: Actual Rent / Share | N1: REMARKS
A2: CPO | B2: January | C2: February | D2: March | E2: April | F2: May | G2: June | H2: January | I2: February | J2: March | K2: April | L2: May | M2: June
A3: InHub EVOxCharge Charging Station | B3: 291828.56 | C3: 317600.81 | D3: 328687.59 | E3: 359690.42 | F3: 365113.19 | G3: =AVERAGE(B3:F3) -> 332584.11 | N3: June is Average of the past few months
A4: REACH (current) | B4: 47165.69 | C4: 56280.74 | D4: 53455.95 | E4: 47385.38 | F4: 66983.08 | G4: =AVERAGE(B4:F4) -> 54254.168 | H4: 19260 | I4: 19260 | J4: 19260 | K4: 20160 | L4: 14910.97 | M4: 18362.58 | N4: June is Average of the past few months
A5: 6NEO (N-Lima) | B5: 3559.44 | C5: 5110.81 | D5: 5343.45 | E5: 7847.21 | F5: 6527.74 | G5: =AVERAGE(B5:F5) -> 5677.73 | H5: 0 | I5: 0 | J5: 0 | K5: 0 | L5: 0 | M5: 0 | N5: June is Average of the past few months
A6: PPT | B6: 2087.4 | C6: 6158.2 | D6: 6592.9 | E6: 7649.5 | F6: 11064.8 | G6: =AVERAGE(B6:F6) -> 6710.56 | H6: 0 | I6: 0 | J6: 0 | K6: 0 | L6: 0 | M6: 0 | N6: June is Average of the past few months
A7: SM MOA Square | B7: =522*'FEES AND ASSUMPTIONS'!$J$6 -> 5220 | C7: =1381.92*'FEES AND ASSUMPTIONS'!$J$6 -> 13819.2 | D7: =2450.87*'FEES AND ASSUMPTIONS'!$J$6 -> 24508.7 | E7: =2714.54*'FEES AND ASSUMPTIONS'!$J$6 -> 27145.4 | F7: =2988.22*'FEES AND ASSUMPTIONS'!$J$6 -> 29882.2 | G7: =3045.73*'FEES AND ASSUMPTIONS'!$J$6 -> 30457.3 | H7: 0 | I7: 0 | J7: 0 | K7: 36000 | L7: 52246 | M7: 40118.72 | N7: Assumed Electricity
A8: SM Lucena | B8: 0 | C8: =769*'FEES AND ASSUMPTIONS'!$J$7 -> 7690 | D8: =951.52*'FEES AND ASSUMPTIONS'!$J$7 -> 9515.2 | E8: =1421.97*'FEES AND ASSUMPTIONS'!$J$7 -> 14219.7 | F8: =1325.57*'FEES AND ASSUMPTIONS'!$J$7 -> 13255.7 | G8: =1123.78*'FEES AND ASSUMPTIONS'!$J$7 -> 11237.8 | H8: 0 | I8: 0 | J8: 0 | K8: 18000 | L8: 26136 | M8: 6420 | N8: Assumed Electricity
A9: SM Rosales | B9: 0 | C9: =182*'FEES AND ASSUMPTIONS'!$J$8 -> 1820 | D9: =366.92*'FEES AND ASSUMPTIONS'!$J$8 -> 3669.2 | E9: =465.02*'FEES AND ASSUMPTIONS'!$J$8 -> 4650.2 | F9: =458.63*'FEES AND ASSUMPTIONS'!$J$8 -> 4586.3 | G9: =301.02*'FEES AND ASSUMPTIONS'!$J$8 -> 3010.2 | H9: 0 | I9: 0 | J9: 0 | K9: 9000 | L9: 13263.48 | M9: 3578.6 | N9: Assumed Electricity
A10: Escala | B10: =60.42*'FEES AND ASSUMPTIONS'!$J$9 -> 604.2 | C10: =27.74*'FEES AND ASSUMPTIONS'!$J$9 -> 277.4 | D10: =97.14*'FEES AND ASSUMPTIONS'!$J$9 -> 971.4 | E10: =183.27*'FEES AND ASSUMPTIONS'!$J$9 -> 1832.7 | F10: =234.22*'FEES AND ASSUMPTIONS'!$J$9 -> 2342.2 | G10: =130.58*'FEES AND ASSUMPTIONS'!$J$9 -> 1305.8 | H10: =60.42*'FEES AND ASSUMPTIONS'!$K$9 -> 725.04 | I10: =27.74*'FEES AND ASSUMPTIONS'!$K$9 -> 332.88 | J10: =97.14*'FEES AND ASSUMPTIONS'!$K$9 -> 1165.68 | K10: =183.27*'FEES AND ASSUMPTIONS'!$K$9 -> 2199.24 | L10: =234.22*'FEES AND ASSUMPTIONS'!$K$9 -> 2810.64 | M10: =130.58*'FEES AND ASSUMPTIONS'!$K$9 -> 1566.96 | N10: Assumed Electricity
A11: ADB | B11: 14944.92 | C11: 12703.52 | D11: 16769.56 | E11: 25071.13 | F11: 27507.06 | G11: 24772.05 | H11: 0 | I11: 0 | J11: 0 | K11: 0 | L11: 0 | M11: 0
A12: SM Sucat | B12: 0 | C12: 0 | D12: 0 | E12: 0 | F12: 0 | G12: 0 | H12: 0 | I12: 0 | J12: 0 | K12: 0 | L12: 0 | M12: 0
A13: World Trade Center | B13: 0 | C13: 0 | D13: =199.42*'FEES AND ASSUMPTIONS'!$J$12 -> 1994.2 | E13: =183.81*'FEES AND ASSUMPTIONS'!$J$12 -> 1838.1 | F13: =78.19*'FEES AND ASSUMPTIONS'!$J$12 -> 781.9 | G13: =63.99*'FEES AND ASSUMPTIONS'!$J$12 -> 639.9 | H13: 0 | I13: 0 | J13: 0 | K13: 0 | L13: 0 | M13: 0 | N13: Assumed Electricity
A14: S Maison at Conrad | B14: 0 | C14: 0 | D14: 0 | E14: =1091.7*'FEES AND ASSUMPTIONS'!$J$13 -> 10917 | F14: =1807.91*'FEES AND ASSUMPTIONS'!$J$13 -> 18079.1 | G14: =1442.9*'FEES AND ASSUMPTIONS'!$J$13 -> 14429 | H14: 0 | I14: 0 | J14: 0 | K14: ='FEES AND ASSUMPTIONS'!$O$13 -> 12000 | L14: ='FEES AND ASSUMPTIONS'!$O$13 -> 12000 | M14: ='FEES AND ASSUMPTIONS'!$O$13 -> 12000 | N14: Assumed Electricity, Assumed Rent
A15: SM Sangandaan | B15: 0 | C15: 0 | D15: 0 | E15: 0 | F15: 0 | G15: 0 | H15: 0 | I15: 0 | J15: 0 | K15: 0 | L15: 0 | M15: 36000
A16: SM Grand Central | B16: 0 | C16: 0 | D16: 0 | E16: 0 | F16: 0 | G16: 0 | H16: 0 | I16: 0 | J16: 0 | K16: 0 | L16: 0 | M16: 36000
A17: SM Valenzuela | B17: 0 | C17: 0 | D17: 0 | E17: 0 | F17: 0 | G17: 0 | H17: 0 | I17: 0 | J17: 0 | K17: 0 | L17: 0 | M17: 36000
A22: CPO - JV
A23: S&R Libis | B23: 0 | C23: 0 | D23: 0 | E23: 0 | F23: =494.31*'FEES AND ASSUMPTIONS'!$J$22 -> 4943.1 | G23: =1593.44*'FEES AND ASSUMPTIONS'!$J$22 -> 15934.4 | H23: 0 | I23: 0 | J23: 0 | K23: 0 | L23: =(175.36*'FEES AND ASSUMPTIONS'!$K$22)+(306.91*'FEES AND ASSUMPTIONS'!$L$22) -> 4016.008 | M23: =(566.91*'FEES AND ASSUMPTIONS'!$K$22)+(1026.53*'FEES AND ASSUMPTIONS'!$L$22) -> 13285.289
A24: S&R Congressional | B24: 0 | C24: 0 | D24: 0 | E24: 0 | F24: =291.79*'FEES AND ASSUMPTIONS'!$J$23 -> 2917.9 | G24: =792.6*'FEES AND ASSUMPTIONS'!$J$23 -> 7926 | H24: 0 | I24: 0 | J24: 0 | K24: 0 | L24: =(116.87*'FEES AND ASSUMPTIONS'!$K$23)+(156.25*'FEES AND ASSUMPTIONS'!$L$23) -> 2251.525 | M24: =(248.5*'FEES AND ASSUMPTIONS'!$K$23)+(544.1*'FEES AND ASSUMPTIONS'!$L$23) -> 6651.83
A25: S&R New Manila | B25: 0 | C25: 0 | D25: 0 | E25: 0 | F25: =454.77*'FEES AND ASSUMPTIONS'!$J$24 -> 4547.7 | G25: =1249.95*'FEES AND ASSUMPTIONS'!$J$24 -> 12499.5 | H25: 0 | I25: 0 | J25: 0 | K25: 0 | L25: =(230.8*'FEES AND ASSUMPTIONS'!$K$24)+(208.71*'FEES AND ASSUMPTIONS'!$L$24) -> 3567.648 | M25: =(514.97*'FEES AND ASSUMPTIONS'!$K$24)+(766.53*'FEES AND ASSUMPTIONS'!$L$24) -> 10607.739
A26: S&R Nuvali | B26: 0 | C26: 0 | D26: 0 | E26: 0 | F26: =559.54*'FEES AND ASSUMPTIONS'!$J$25 -> 5595.4 | G26: =1366.45*'FEES AND ASSUMPTIONS'!$J$25 -> 13664.5 | H26: 0 | I26: 0 | J26: 0 | K26: 0 | L26: =(110.97*'FEES AND ASSUMPTIONS'!$K$25)+(445.94*'FEES AND ASSUMPTIONS'!$L$25) -> 4756.547 | M26: =(481.53*'FEES AND ASSUMPTIONS'!$K$25)+(901.77*'FEES AND ASSUMPTIONS'!$L$25) -> 11547.051

Sheet ESTIMATED OPEX
B1: Estimated Electricity Cost | H1: Estimated Rent / Share | N1: REMARKS
A2: CPO | B2: July | C2: August | D2: September | E2: October | F2: November | G2: December | H2: July | I2: August | J2: September | K2: October | L2: November | M2: December
A3: InHub EVOxCharge Charging Station | B3: =(('FEES AND ASSUMPTIONS'!D2*'FEES AND ASSUMPTIONS'!F2)+('FEES AND ASSUMPTIONS'!E2*'FEES AND ASSUMPTIONS'!G2))*'FEES AND ASSUMPTIONS'!J2 -> 212760 | C3: =B3*1.02 -> 217015.2 | D3: =C3*1.02 -> 221355.5 | E3: =D3*1.02 -> 225782.61 | F3: =E3*1.02 -> 230298.27 | G3: =F3*1.02 -> 234904.23 | H3: 0 | I3: 0 | J3: 0 | K3: 0 | L3: 0 | M3: 0
A4: REACH (current) | B4: =(('FEES AND ASSUMPTIONS'!D3*'FEES AND ASSUMPTIONS'!F3)+('FEES AND ASSUMPTIONS'!E3*'FEES AND ASSUMPTIONS'!G3))*'FEES AND ASSUMPTIONS'!J3 -> 23652 | C4: =B4*1.02 -> 24125.04 | D4: =C4*1.02 -> 24607.541 | E4: =D4*1.02 -> 25099.692 | F4: =E4*1.02 -> 25601.685 | G4: =F4*1.02 -> 26113.719 | H4: ='FEES AND ASSUMPTIONS'!$O$3 -> 20160 | I4: ='FEES AND ASSUMPTIONS'!$O$3 -> 20160 | J4: ='FEES AND ASSUMPTIONS'!$O$3 -> 20160 | K4: ='FEES AND ASSUMPTIONS'!$O$3 -> 20160 | L4: ='FEES AND ASSUMPTIONS'!$O$3 -> 20160 | M4: ='FEES AND ASSUMPTIONS'!$O$3 -> 20160
A5: 6NEO (N-Lima) | B5: =(('FEES AND ASSUMPTIONS'!D4*'FEES AND ASSUMPTIONS'!F4)+('FEES AND ASSUMPTIONS'!E4*'FEES AND ASSUMPTIONS'!G4))*'FEES AND ASSUMPTIONS'!J4 -> 8508 | C5: =B5*1.02 -> 8678.16 | D5: =C5*1.02 -> 8851.7232 | E5: =D5*1.02 -> 9028.7577 | F5: =E5*1.02 -> 9209.3328 | G5: =F5*1.02 -> 9393.5195 | H5: 0 | I5: 0 | J5: 0 | K5: 0 | L5: 0 | M5: 0
A6: PPT | B6: =(('FEES AND ASSUMPTIONS'!D5*'FEES AND ASSUMPTIONS'!F5)+('FEES AND ASSUMPTIONS'!E5*'FEES AND ASSUMPTIONS'!G5))*'FEES AND ASSUMPTIONS'!J5 -> 6000 | C6: =B6*1.02 -> 6120 | D6: =C6*1.02 -> 6242.4 | E6: =D6*1.02 -> 6367.248 | F6: =E6*1.02 -> 6494.593 | G6: =F6*1.02 -> 6624.4848 | H6: 0 | I6: 0 | J6: 0 | K6: 0 | L6: 0 | M6: 0
A7: SM MOA Square | B7: =(('FEES AND ASSUMPTIONS'!D6*'FEES AND ASSUMPTIONS'!F6)+('FEES AND ASSUMPTIONS'!E6*'FEES AND ASSUMPTIONS'!G6))*'FEES AND ASSUMPTIONS'!J6 -> 30000 | C7: =B7*1.02 -> 30600 | D7: =C7*1.02 -> 31212 | E7: =D7*1.02 -> 31836.24 | F7: =E7*1.02 -> 32472.965 | G7: =F7*1.02 -> 33122.424 | H7: ='FEES AND ASSUMPTIONS'!$O$6 -> 18000 | I7: ='FEES AND ASSUMPTIONS'!$O$6 -> 18000 | J7: ='FEES AND ASSUMPTIONS'!$O$6 -> 18000 | K7: ='FEES AND ASSUMPTIONS'!$O$6 -> 18000 | L7: ='FEES AND ASSUMPTIONS'!$O$6 -> 18000 | M7: ='FEES AND ASSUMPTIONS'!$O$6 -> 18000
A8: SM Lucena | B8: =(('FEES AND ASSUMPTIONS'!D7*'FEES AND ASSUMPTIONS'!F7)+('FEES AND ASSUMPTIONS'!E7*'FEES AND ASSUMPTIONS'!G7))*'FEES AND ASSUMPTIONS'!J7 -> 14000 | C8: =B8*1.02 -> 14280 | D8: =C8*1.02 -> 14565.6 | E8: =D8*1.02 -> 14856.912 | F8: =E8*1.02 -> 15154.05 | G8: =F8*1.02 -> 15457.131 | H8: ='FEES AND ASSUMPTIONS'!$O$7 -> 6000 | I8: ='FEES AND ASSUMPTIONS'!$O$7 -> 6000 | J8: ='FEES AND ASSUMPTIONS'!$O$7 -> 6000 | K8: ='FEES AND ASSUMPTIONS'!$O$7 -> 6000 | L8: ='FEES AND ASSUMPTIONS'!$O$7 -> 6000 | M8: ='FEES AND ASSUMPTIONS'!$O$7 -> 6000
A9: SM Rosales | B9: =(('FEES AND ASSUMPTIONS'!D8*'FEES AND ASSUMPTIONS'!F8)+('FEES AND ASSUMPTIONS'!E8*'FEES AND ASSUMPTIONS'!G8))*'FEES AND ASSUMPTIONS'!J8 -> 3500 | C9: =B9*1.02 -> 3570 | D9: =C9*1.02 -> 3641.4 | E9: =D9*1.02 -> 3714.228 | F9: =E9*1.02 -> 3788.5126 | G9: =F9*1.02 -> 3864.2828 | H9: ='FEES AND ASSUMPTIONS'!$O$8 -> 3000 | I9: ='FEES AND ASSUMPTIONS'!$O$8 -> 3000 | J9: ='FEES AND ASSUMPTIONS'!$O$8 -> 3000 | K9: ='FEES AND ASSUMPTIONS'!$O$8 -> 3000 | L9: ='FEES AND ASSUMPTIONS'!$O$8 -> 3000 | M9: ='FEES AND ASSUMPTIONS'!$O$8 -> 3000
A10: Escala | B10: =(('FEES AND ASSUMPTIONS'!D9*'FEES AND ASSUMPTIONS'!F9)+('FEES AND ASSUMPTIONS'!E9*'FEES AND ASSUMPTIONS'!G9))*'FEES AND ASSUMPTIONS'!J9 -> 1400 | C10: =B10*1.02 -> 1428 | D10: =C10*1.02 -> 1456.56 | E10: =D10*1.02 -> 1485.6912 | F10: =E10*1.02 -> 1515.405 | G10: =F10*1.02 -> 1545.7131 | H10: ='FEES AND ASSUMPTIONS'!D9*'FEES AND ASSUMPTIONS'!F9*'FEES AND ASSUMPTIONS'!$K$9 -> 1680 | I10: =H10*1.02 -> 1713.6 | J10: =I10*1.02 -> 1747.872 | K10: =J10*1.02 -> 1782.8294 | L10: =K10*1.02 -> 1818.486 | M10: =L10*1.02 -> 1854.8557
A11: ADB | B11: =(('FEES AND ASSUMPTIONS'!D10*'FEES AND ASSUMPTIONS'!F10)+('FEES AND ASSUMPTIONS'!E10*'FEES AND ASSUMPTIONS'!G10))*'FEES AND ASSUMPTIONS'!J10 -> 15390 | C11: =B11*1.02 -> 15697.8 | D11: =C11*1.02 -> 16011.756 | E11: =D11*1.02 -> 16331.991 | F11: =E11*1.02 -> 16658.631 | G11: =F11*1.02 -> 16991.804 | H11: 0 | I11: 0 | J11: 0 | K11: 0 | L11: 0 | M11: 0
A12: SM Sucat | B12: =(('FEES AND ASSUMPTIONS'!D11*'FEES AND ASSUMPTIONS'!F11)+('FEES AND ASSUMPTIONS'!E11*'FEES AND ASSUMPTIONS'!G11))*'FEES AND ASSUMPTIONS'!J11 -> 14000 | C12: =B12*1.02 -> 14280 | D12: =C12*1.02 -> 14565.6 | E12: =D12*1.02 -> 14856.912 | F12: =E12*1.02 -> 15154.05 | G12: =F12*1.02 -> 15457.131 | H12: ='FEES AND ASSUMPTIONS'!$O$11 -> 12000 | I12: ='FEES AND ASSUMPTIONS'!$O$11 -> 12000 | J12: ='FEES AND ASSUMPTIONS'!$O$11 -> 12000 | K12: ='FEES AND ASSUMPTIONS'!$O$11 -> 12000 | L12: ='FEES AND ASSUMPTIONS'!$O$11 -> 12000 | M12: ='FEES AND ASSUMPTIONS'!$O$11 -> 12000
A13: World Trade Center | B13: =(('FEES AND ASSUMPTIONS'!D12*'FEES AND ASSUMPTIONS'!F12)+('FEES AND ASSUMPTIONS'!E12*'FEES AND ASSUMPTIONS'!G12))*'FEES AND ASSUMPTIONS'!J12 -> 2000 | C13: =B13*1.02 -> 2040 | D13: =C13*1.02 -> 2080.8 | E13: =D13*1.02 -> 2122.416 | F13: =E13*1.02 -> 2164.8643 | G13: =F13*1.02 -> 2208.1616 | H13: 0 | I13: 0 | J13: 0 | K13: 0 | L13: 0 | M13: 0
A14: S Maison at Conrad | B14: =(('FEES AND ASSUMPTIONS'!D13*'FEES AND ASSUMPTIONS'!F13)+('FEES AND ASSUMPTIONS'!E13*'FEES AND ASSUMPTIONS'!G13))*'FEES AND ASSUMPTIONS'!J13 -> 14000 | C14: =B14*1.02 -> 14280 | D14: =C14*1.02 -> 14565.6 | E14: =D14*1.02 -> 14856.912 | F14: =E14*1.02 -> 15154.05 | G14: =F14*1.02 -> 15457.131 | H14: ='FEES AND ASSUMPTIONS'!$O$13 -> 12000 | I14: ='FEES AND ASSUMPTIONS'!$O$13 -> 12000 | J14: ='FEES AND ASSUMPTIONS'!$O$13 -> 12000 | K14: ='FEES AND ASSUMPTIONS'!$O$13 -> 12000 | L14: ='FEES AND ASSUMPTIONS'!$O$13 -> 12000 | M14: ='FEES AND ASSUMPTIONS'!$O$13 -> 12000
A15: SM Sangandaan | B15: =(('FEES AND ASSUMPTIONS'!D14*'FEES AND ASSUMPTIONS'!F14)+('FEES AND ASSUMPTIONS'!E14*'FEES AND ASSUMPTIONS'!G14))*'FEES AND ASSUMPTIONS'!J14 -> 14000 | C15: =B15*1.02 -> 14280 | D15: =C15*1.02 -> 14565.6 | E15: =D15*1.02 -> 14856.912 | F15: =E15*1.02 -> 15154.05 | G15: =F15*1.02 -> 15457.131 | H15: ='FEES AND ASSUMPTIONS'!$O$14 -> 12000 | I15: ='FEES AND ASSUMPTIONS'!$O$14 -> 12000 | J15: ='FEES AND ASSUMPTIONS'!$O$14 -> 12000 | K15: ='FEES AND ASSUMPTIONS'!$O$14 -> 12000 | L15: ='FEES AND ASSUMPTIONS'!$O$14 -> 12000 | M15: ='FEES AND ASSUMPTIONS'!$O$14 -> 12000
A16: SM Grand Central | B16: =(('FEES AND ASSUMPTIONS'!D15*'FEES AND ASSUMPTIONS'!F15)+('FEES AND ASSUMPTIONS'!E15*'FEES AND ASSUMPTIONS'!G15))*'FEES AND ASSUMPTIONS'!J15 -> 14000 | C16: =B16*1.02 -> 14280 | D16: =C16*1.02 -> 14565.6 | E16: =D16*1.02 -> 14856.912 | F16: =E16*1.02 -> 15154.05 | G16: =F16*1.02 -> 15457.131 | H16: ='FEES AND ASSUMPTIONS'!$O$15 -> 12000 | I16: ='FEES AND ASSUMPTIONS'!$O$15 -> 12000 | J16: ='FEES AND ASSUMPTIONS'!$O$15 -> 12000 | K16: ='FEES AND ASSUMPTIONS'!$O$15 -> 12000 | L16: ='FEES AND ASSUMPTIONS'!$O$15 -> 12000 | M16: ='FEES AND ASSUMPTIONS'!$O$15 -> 12000
A17: SM Valenzuela | B17: =(('FEES AND ASSUMPTIONS'!D16*'FEES AND ASSUMPTIONS'!F16)+('FEES AND ASSUMPTIONS'!E16*'FEES AND ASSUMPTIONS'!G16))*'FEES AND ASSUMPTIONS'!J16 -> 14000 | C17: =B17*1.02 -> 14280 | D17: =C17*1.02 -> 14565.6 | E17: =D17*1.02 -> 14856.912 | F17: =E17*1.02 -> 15154.05 | G17: =F17*1.02 -> 15457.131 | H17: ='FEES AND ASSUMPTIONS'!$O$16 -> 12000 | I17: ='FEES AND ASSUMPTIONS'!$O$16 -> 12000 | J17: ='FEES AND ASSUMPTIONS'!$O$16 -> 12000 | K17: ='FEES AND ASSUMPTIONS'!$O$16 -> 12000 | L17: ='FEES AND ASSUMPTIONS'!$O$16 -> 12000 | M17: ='FEES AND ASSUMPTIONS'!$O$16 -> 12000
A22: CPO - JV
A23: S&R Libis | B23: =(('FEES AND ASSUMPTIONS'!D22*'FEES AND ASSUMPTIONS'!F22)+('FEES AND ASSUMPTIONS'!E22*'FEES AND ASSUMPTIONS'!G22))*'FEES AND ASSUMPTIONS'!J22 -> 13000 | C23: =B23*1.02 -> 13260 | D23: =C23*1.02 -> 13525.2 | E23: =D23*1.02 -> 13795.704 | F23: =E23*1.02 -> 14071.618 | G23: =F23*1.02 -> 14353.05 | H23: =('FEES AND ASSUMPTIONS'!D22*'FEES AND ASSUMPTIONS'!F22*'FEES AND ASSUMPTIONS'!K22)+('FEES AND ASSUMPTIONS'!E22*'FEES AND ASSUMPTIONS'!G22*'FEES AND ASSUMPTIONS'!L22) -> 10920 | I23: =H23*1.02 -> 11138.4 | J23: =I23*1.02 -> 11361.168 | K23: =J23*1.02 -> 11588.391 | L23: =K23*1.02 -> 11820.159 | M23: =L23*1.02 -> 12056.562
A24: S&R Congressional | B24: =(('FEES AND ASSUMPTIONS'!D23*'FEES AND ASSUMPTIONS'!F23)+('FEES AND ASSUMPTIONS'!E23*'FEES AND ASSUMPTIONS'!G23))*'FEES AND ASSUMPTIONS'!J23 -> 13000 | C24: =B24*1.02 -> 13260 | D24: =C24*1.02 -> 13525.2 | E24: =D24*1.02 -> 13795.704 | F24: =E24*1.02 -> 14071.618 | G24: =F24*1.02 -> 14353.05 | H24: =('FEES AND ASSUMPTIONS'!D23*'FEES AND ASSUMPTIONS'!F23*'FEES AND ASSUMPTIONS'!K23)+('FEES AND ASSUMPTIONS'!E23*'FEES AND ASSUMPTIONS'!G23*'FEES AND ASSUMPTIONS'!L23) -> 10920 | I24: =H24*1.02 -> 11138.4 | J24: =I24*1.02 -> 11361.168 | K24: =J24*1.02 -> 11588.391 | L24: =K24*1.02 -> 11820.159 | M24: =L24*1.02 -> 12056.562
A25: S&R New Manila | B25: =(('FEES AND ASSUMPTIONS'!D24*'FEES AND ASSUMPTIONS'!F24)+('FEES AND ASSUMPTIONS'!E24*'FEES AND ASSUMPTIONS'!G24))*'FEES AND ASSUMPTIONS'!J24 -> 13000 | C25: =B25*1.02 -> 13260 | D25: =C25*1.02 -> 13525.2 | E25: =D25*1.02 -> 13795.704 | F25: =E25*1.02 -> 14071.618 | G25: =F25*1.02 -> 14353.05 | H25: =('FEES AND ASSUMPTIONS'!D24*'FEES AND ASSUMPTIONS'!F24*'FEES AND ASSUMPTIONS'!K24)+('FEES AND ASSUMPTIONS'!E24*'FEES AND ASSUMPTIONS'!G24*'FEES AND ASSUMPTIONS'!L24) -> 10920 | I25: =H25*1.02 -> 11138.4 | J25: =I25*1.02 -> 11361.168 | K25: =J25*1.02 -> 11588.391 | L25: =K25*1.02 -> 11820.159 | M25: =L25*1.02 -> 12056.562
A26: S&R Nuvali | B26: =(('FEES AND ASSUMPTIONS'!D25*'FEES AND ASSUMPTIONS'!F25)+('FEES AND ASSUMPTIONS'!E25*'FEES AND ASSUMPTIONS'!G25))*'FEES AND ASSUMPTIONS'!J25 -> 13000 | C26: =B26*1.02 -> 13260 | D26: =C26*1.02 -> 13525.2 | E26: =D26*1.02 -> 13795.704 | F26: =E26*1.02 -> 14071.618 | G26: =F26*1.02 -> 14353.05 | H26: =('FEES AND ASSUMPTIONS'!D25*'FEES AND ASSUMPTIONS'!F25*'FEES AND ASSUMPTIONS'!K25)+('FEES AND ASSUMPTIONS'!E25*'FEES AND ASSUMPTIONS'!G25*'FEES AND ASSUMPTIONS'!L25) -> 10920 | I26: =H26*1.02 -> 11138.4 | J26: =I26*1.02 -> 11361.168 | K26: =J26*1.02 -> 11588.391 | L26: =K26*1.02 -> 11820.159 | M26: =L26*1.02 -> 12056.562

Sheet ACTUAL AND ESTIMATED REVENUE
B1: ACTUAL REVENUE | H1: ESTIMATED REVENUE
A2: CPO | B2: January | C2: February | D2: March | E2: April | F2: May | G2: June | H2: July | I2: August | J2: September | K2: October | L2: November | M2: December | N2: TOTAL
A3: InHub EVOxCharge Charging Station | B3: 557427.2 | C3: 573407.94 | D3: 631664.14 | E3: 551425.34 | F3: 681508.7 | G3: 535263.34 | H3: =('FEES AND ASSUMPTIONS'!D2*'FEES AND ASSUMPTIONS'!H2*'FEES AND ASSUMPTIONS'!F2)+('FEES AND ASSUMPTIONS'!E2*'FEES AND ASSUMPTIONS'!I2*'FEES AND ASSUMPTIONS'!G2) -> 504000 | I3: =H3*1.02 -> 514080 | J3: =I3*1.02 -> 524361.6 | K3: =J3*1.02 -> 534848.83 | L3: =K3*1.02 -> 545545.81 | M3: =L3*1.02 -> 556456.72 | N3: =SUM(B3:M3) -> 6709989.6
A4: REACH (current) | B4: =69329+'FEES AND ASSUMPTIONS'!$Q$3 -> 106829 | C4: =79775+'FEES AND ASSUMPTIONS'!$Q$3 -> 117275 | D4: =114028+'FEES AND ASSUMPTIONS'!$Q$3 -> 151528 | E4: =98023+'FEES AND ASSUMPTIONS'!$Q$3 -> 135523 | F4: =101438+'FEES AND ASSUMPTIONS'!$Q$3 -> 138938 | G4: =114533+'FEES AND ASSUMPTIONS'!$Q$3 -> 152033 | H4: =('FEES AND ASSUMPTIONS'!$D$3+'FEES AND ASSUMPTIONS'!$E$3)*2*'FEES AND ASSUMPTIONS'!$H$3+'FEES AND ASSUMPTIONS'!$Q$3 -> 131100 | I4: =H4*1.02 -> 133722 | J4: =I4*1.02 -> 136396.44 | K4: =J4*1.02 -> 139124.37 | L4: =K4*1.02 -> 141906.86 | M4: =L4*1.02 -> 144744.99 | N4: =SUM(B4:M4) -> 1629120.7
A5: 6NEO (N-Lima) | B5: 13659 | C5: 12850 | D5: 27514 | E5: 30527 | F5: 25224 | G5: 26561 | H5: ='FEES AND ASSUMPTIONS'!D4*'FEES AND ASSUMPTIONS'!F4*'FEES AND ASSUMPTIONS'!H4 -> 24000 | I5: =H5*1.02 -> 24480 | J5: =I5*1.02 -> 24969.6 | K5: =J5*1.02 -> 25468.992 | L5: =K5*1.02 -> 25978.372 | M5: =L5*1.02 -> 26497.939 | N5: =SUM(B5:M5) -> 287729.9
A6: PPT | B6: 8381 | C6: 13437 | D6: 22998 | E6: 37546 | F6: 33986 | G6: 24343 | H6: ='FEES AND ASSUMPTIONS'!E5*'FEES AND ASSUMPTIONS'!G5*'FEES AND ASSUMPTIONS'!I5 -> 15600 | I6: =H6*1.02 -> 15912 | J6: =I6*1.02 -> 16230.24 | K6: =J6*1.02 -> 16554.845 | L6: =K6*1.02 -> 16885.942 | M6: =L6*1.02 -> 17223.661 | N6: =SUM(B6:M6) -> 239097.69
A7: SM MOA Square | B7: 0 | C7: 36094 | D7: 87764 | E7: 83043 | F7: 93083 | G7: 91312 | H7: ='FEES AND ASSUMPTIONS'!D6*'FEES AND ASSUMPTIONS'!F6*'FEES AND ASSUMPTIONS'!H6 -> 75000 | I7: =H7*1.02 -> 76500 | J7: =I7*1.02 -> 78030 | K7: =J7*1.02 -> 79590.6 | L7: =K7*1.02 -> 81182.412 | M7: =L7*1.02 -> 82806.06 | N7: =SUM(B7:M7) -> 864405.07
A8: SM Lucena | B8: 0 | C8: 20382 | D8: 36628 | E8: 46189 | F8: 41899 | G8: 43154 | H8: ='FEES AND ASSUMPTIONS'!D7*'FEES AND ASSUMPTIONS'!F7*'FEES AND ASSUMPTIONS'!H7 -> 35000 | I8: =H8*1.02 -> 35700 | J8: =I8*1.02 -> 36414 | K8: =J8*1.02 -> 37142.28 | L8: =K8*1.02 -> 37885.126 | M8: =L8*1.02 -> 38642.828 | N8: =SUM(B8:M8) -> 409036.23
A9: SM Rosales | B9: 0 | C9: 5274 | D9: 14593 | E9: 15286 | F9: 13706 | G9: 10266 | H9: ='FEES AND ASSUMPTIONS'!D8*'FEES AND ASSUMPTIONS'!F8*'FEES AND ASSUMPTIONS'!H8 -> 8750 | I9: =H9*1.02 -> 8925 | J9: =I9*1.02 -> 9103.5 | K9: =J9*1.02 -> 9285.57 | L9: =K9*1.02 -> 9471.2814 | M9: =L9*1.02 -> 9660.707 | N9: =SUM(B9:M9) -> 114321.06
A10: Escala | B10: 2356 | C10: 1068 | D10: 3794 | E10: 8221 | F10: 10766 | G10: 6191 | H10: ='FEES AND ASSUMPTIONS'!D9*'FEES AND ASSUMPTIONS'!F9*'FEES AND ASSUMPTIONS'!H9 -> 5180 | I10: =H10*1.02 -> 5283.6 | J10: =I10*1.02 -> 5389.272 | K10: =J10*1.02 -> 5497.0574 | L10: =K10*1.02 -> 5606.9986 | M10: =L10*1.02 -> 5719.1386 | N10: =SUM(B10:M10) -> 65072.067
A11: ADB | B11: 36794 | C11: 31276 | D11: 51285 | E11: 61922 | F11: 67722 | G11: 60988 | H11: ='FEES AND ASSUMPTIONS'!D10*'FEES AND ASSUMPTIONS'!F10*'FEES AND ASSUMPTIONS'!H10 -> 37890 | I11: =H11*1.02 -> 38647.8 | J11: =I11*1.02 -> 39420.756 | K11: =J11*1.02 -> 40209.171 | L11: =K11*1.02 -> 41013.355 | M11: =L11*1.02 -> 41833.622 | N11: =SUM(B11:M11) -> 549001.7
A12: SM Sucat | B12: 0 | C12: 0 | D12: 0 | E12: 0 | F12: 0 | G12: 0 | H12: ='FEES AND ASSUMPTIONS'!D11*'FEES AND ASSUMPTIONS'!F11*'FEES AND ASSUMPTIONS'!H11 -> 35000 | I12: =H12*1.02 -> 35700 | J12: =I12*1.02 -> 36414 | K12: =J12*1.02 -> 37142.28 | L12: =K12*1.02 -> 37885.126 | M12: =L12*1.02 -> 38642.828 | N12: =SUM(B12:M12) -> 220784.23
A13: World Trade Center | B13: 0 | C13: 0 | D13: 7443 | E13: 6684 | F13: 4106 | G13: 2600 | H13: ='FEES AND ASSUMPTIONS'!D12*'FEES AND ASSUMPTIONS'!F12*'FEES AND ASSUMPTIONS'!H12 -> 6000 | I13: =H13*1.02 -> 6120 | J13: =I13*1.02 -> 6242.4 | K13: =J13*1.02 -> 6367.248 | L13: =K13*1.02 -> 6494.593 | M13: =L13*1.02 -> 6624.4848 | N13: =SUM(B13:M13) -> 58681.726
A14: S Maison at Conrad | B14: 0 | C14: 0 | D14: 0 | E14: 32052 | F14: 54418 | G14: 43492 | H14: ='FEES AND ASSUMPTIONS'!D13*'FEES AND ASSUMPTIONS'!F13*'FEES AND ASSUMPTIONS'!H13 -> 35000 | I14: =H14*1.02 -> 35700 | J14: =I14*1.02 -> 36414 | K14: =J14*1.02 -> 37142.28 | L14: =K14*1.02 -> 37885.126 | M14: =L14*1.02 -> 38642.828 | N14: =SUM(B14:M14) -> 350746.23
A15: SM Sangandaan | B15: 0 | C15: 0 | D15: 0 | E15: 0 | F15: 0 | G15: 0 | H15: ='FEES AND ASSUMPTIONS'!D14*'FEES AND ASSUMPTIONS'!F14*'FEES AND ASSUMPTIONS'!H14 -> 35000 | I15: =H15*1.02 -> 35700 | J15: =I15*1.02 -> 36414 | K15: =J15*1.02 -> 37142.28 | L15: =K15*1.02 -> 37885.126 | M15: =L15*1.02 -> 38642.828 | N15: =SUM(B15:M15) -> 220784.23
A16: SM Grand Central | B16: 0 | C16: 0 | D16: 0 | E16: 0 | F16: 0 | G16: 0 | H16: ='FEES AND ASSUMPTIONS'!D15*'FEES AND ASSUMPTIONS'!F15*'FEES AND ASSUMPTIONS'!H15 -> 35000 | I16: =H16*1.02 -> 35700 | J16: =I16*1.02 -> 36414 | K16: =J16*1.02 -> 37142.28 | L16: =K16*1.02 -> 37885.126 | M16: =L16*1.02 -> 38642.828 | N16: =SUM(B16:M16) -> 220784.23
A17: SM Valenzuela | B17: 0 | C17: 0 | D17: 0 | E17: 0 | F17: 0 | G17: 0 | H17: ='FEES AND ASSUMPTIONS'!D16*'FEES AND ASSUMPTIONS'!F16*'FEES AND ASSUMPTIONS'!H16 -> 35000 | I17: =H17*1.02 -> 35700 | J17: =I17*1.02 -> 36414 | K17: =J17*1.02 -> 37142.28 | L17: =K17*1.02 -> 37885.126 | M17: =L17*1.02 -> 38642.828 | N17: =SUM(B17:M17) -> 220784.23
A22: CPO - JV
A23: S&R Libis | B23: 0 | C23: 0 | D23: 0 | E23: 0 | F23: 15066 | G23: 50121 | H23: =('FEES AND ASSUMPTIONS'!D22*'FEES AND ASSUMPTIONS'!H22*'FEES AND ASSUMPTIONS'!F22)+('FEES AND ASSUMPTIONS'!E22*'FEES AND ASSUMPTIONS'!I22*'FEES AND ASSUMPTIONS'!G22) -> 38800 | I23: =H23*1.02 -> 39576 | J23: =I23*1.02 -> 40367.52 | K23: =J23*1.02 -> 41174.87 | L23: =K23*1.02 -> 41998.368 | M23: =L23*1.02 -> 42838.335 | N23: =SUM(B23:M23) -> 309942.09
A24: S&R Congressional | B24: 0 | C24: 0 | D24: 0 | E24: 0 | F24: 12889 | G24: 24923 | H24: =('FEES AND ASSUMPTIONS'!D23*'FEES AND ASSUMPTIONS'!H23*'FEES AND ASSUMPTIONS'!F23)+('FEES AND ASSUMPTIONS'!E23*'FEES AND ASSUMPTIONS'!I23*'FEES AND ASSUMPTIONS'!G23) -> 38800 | I24: =H24*1.02 -> 39576 | J24: =I24*1.02 -> 40367.52 | K24: =J24*1.02 -> 41174.87 | L24: =K24*1.02 -> 41998.368 | M24: =L24*1.02 -> 42838.335 | N24: =SUM(B24:M24) -> 282567.09
A25: S&R New Manila | B25: 0 | C25: 0 | D25: 0 | E25: 0 | F25: 18045 | G25: 48372 | H25: =('FEES AND ASSUMPTIONS'!D24*'FEES AND ASSUMPTIONS'!H24*'FEES AND ASSUMPTIONS'!F24)+('FEES AND ASSUMPTIONS'!E24*'FEES AND ASSUMPTIONS'!I24*'FEES AND ASSUMPTIONS'!G24) -> 38800 | I25: =H25*1.02 -> 39576 | J25: =I25*1.02 -> 40367.52 | K25: =J25*1.02 -> 41174.87 | L25: =K25*1.02 -> 41998.368 | M25: =L25*1.02 -> 42838.335 | N25: =SUM(B25:M25) -> 311172.09
A26: S&R Nuvali | B26: 0 | C26: 0 | D26: 0 | E26: 0 | F26: 13889 | G26: 39514 | H26: =('FEES AND ASSUMPTIONS'!D25*'FEES AND ASSUMPTIONS'!H25*'FEES AND ASSUMPTIONS'!F25)+('FEES AND ASSUMPTIONS'!E25*'FEES AND ASSUMPTIONS'!I25*'FEES AND ASSUMPTIONS'!G25) -> 38800 | I26: =H26*1.02 -> 39576 | J26: =I26*1.02 -> 40367.52 | K26: =J26*1.02 -> 41174.87 | L26: =K26*1.02 -> 41998.368 | M26: =L26*1.02 -> 42838.335 | N26: =SUM(B26:M26) -> 298158.09

Sheet CAPEX
A1: SITES | B1: Charger | C1: Installation | D1: Marketing | E1: Others | F1: TOTAL CAPEX
A2: CPO
A3: InHub EVOxCharge Charging Station | F3: =SUM(B3:E3) -> 0
A4: REACH (current) | F4: =SUM(B4:E4) -> 0
A5: 6NEO (N-Lima) | F5: =SUM(B5:E5) -> 0
A6: PPT | F6: =SUM(B6:E6) -> 0
A7: SM MOA Square | C7: =311640+76074.92 -> 387714.92 | D7: 90500 | F7: =SUM(B7:E7) -> 478214.92
A8: SM Lucena | D8: 64380 | F8: =SUM(B8:E8) -> 64380
A9: SM Rosales | D9: 45590 | F9: =SUM(B9:E9) -> 45590
A10: Escala | F10: =SUM(B10:E10) -> 0
A11: ADB | F11: =SUM(B11:E11) -> 0
A12: SM Sucat | C12: 268000 | F12: =SUM(B12:E12) -> 268000
A13: World Trade Center | F13: =SUM(B13:E13) -> 0
A14: S Maison at Conrad | C14: 295021.17 | D14: 52000 | F14: =SUM(B14:E14) -> 347021.17
A15: SM Sangandaan | C15: =238000+21000 -> 259000 | F15: =SUM(B15:E15) -> 259000
A16: SM Grand Central | C16: 353000 | F16: =SUM(B16:E16) -> 353000
A17: SM Valenzuela | C17: 227517.71 | F17: =SUM(B17:E17) -> 227517.71
F18: =SUM(B18:E18) -> 0
F19: =SUM(B19:E19) -> 0
F20: =SUM(B20:E20) -> 0
F21: =SUM(B21:E21) -> 0
A22: CPO - JV
A23: S&R Libis | D23: =97000+25000 -> 122000 | E23: =30000 -> 30000 | F23: =SUM(B23:E23) -> 152000
A24: S&R Congressional | D24: =90500+25000 -> 115500 | E24: =30000 -> 30000 | F24: =SUM(B24:E24) -> 145500
A25: S&R New Manila | D25: =97000+25000 -> 122000 | E25: =30000 -> 30000 | F25: =SUM(B25:E25) -> 152000
A26: S&R Nuvali | C26: 8000 | D26: =100000+25000 -> 125000 | E26: =30000 -> 30000 | F26: =SUM(B26:E26) -> 163000
F27: =SUM(B27:E27) -> 0
F28: =SUM(B28:E28) -> 0
F29: =SUM(B29:E29) -> 0
F30: =SUM(B30:E30) -> 0

Sheet OVERALL
A1: CPO | B1: Revenue | C1: Actual Electricity Cost | D1: Estimated Electricity Cost | E1: Actual Rental/Share | F1: Estimated Rental / Share | G1: Estimated Income for the year 2026
A2: InHub EVOxCharge Charging Station | B2: ='ACTUAL AND ESTIMATED REVENUE'!N3 -> 6709989.6 | C2: =sum('ACTUAL OPEX (JAN-JUN)'!B3:G3) -> 1995504.7 | D2: =sum('ESTIMATED OPEX'!B3:G3) -> 1342115.8 | E2: =sum('ACTUAL OPEX (JAN-JUN)'!H3:M3) -> 0 | F2: =sum('ESTIMATED OPEX'!H3:M3) -> 0 | G2: =B2-(C2+D2+E2+F2) -> 3372369.1
A3: REACH (current) | B3: ='ACTUAL AND ESTIMATED REVENUE'!N4 -> 1629120.7 | C3: =sum('ACTUAL OPEX (JAN-JUN)'!B4:G4) -> 325525.01 | D3: =sum('ESTIMATED OPEX'!B4:G4) -> 149199.68 | E3: =sum('ACTUAL OPEX (JAN-JUN)'!H4:M4) -> 111213.55 | F3: =sum('ESTIMATED OPEX'!H4:M4) -> 120960 | G3: =B3-(C3+D3+E3+F3) -> 922222.42
A4: 6NEO (N-Lima) | B4: ='ACTUAL AND ESTIMATED REVENUE'!N5 -> 287729.9 | C4: =sum('ACTUAL OPEX (JAN-JUN)'!B5:G5) -> 34066.38 | D4: =sum('ESTIMATED OPEX'!B5:G5) -> 53669.493 | E4: =sum('ACTUAL OPEX (JAN-JUN)'!H5:M5) -> 0 | F4: =sum('ESTIMATED OPEX'!H5:M5) -> 0 | G4: =B4-(C4+D4+E4+F4) -> 199994.03
A5: PPT | B5: ='ACTUAL AND ESTIMATED REVENUE'!N6 -> 239097.69 | C5: =sum('ACTUAL OPEX (JAN-JUN)'!B6:G6) -> 40263.36 | D5: =sum('ESTIMATED OPEX'!B6:G6) -> 37848.726 | E5: =sum('ACTUAL OPEX (JAN-JUN)'!H6:M6) -> 0 | F5: =sum('ESTIMATED OPEX'!H6:M6) -> 0 | G5: =B5-(C5+D5+E5+F5) -> 160985.6
A6: SM MOA Square | B6: ='ACTUAL AND ESTIMATED REVENUE'!N7 -> 864405.07 | C6: =sum('ACTUAL OPEX (JAN-JUN)'!B7:G7) -> 131032.8 | D6: =sum('ESTIMATED OPEX'!B7:G7) -> 189243.63 | E6: =sum('ACTUAL OPEX (JAN-JUN)'!H7:M7) -> 128364.72 | F6: =sum('ESTIMATED OPEX'!H7:M7) -> 108000 | G6: =B6-(C6+D6+E6+F6) -> 307763.92
A7: SM Lucena | B7: ='ACTUAL AND ESTIMATED REVENUE'!N8 -> 409036.23 | C7: =sum('ACTUAL OPEX (JAN-JUN)'!B8:G8) -> 55918.4 | D7: =sum('ESTIMATED OPEX'!B8:G8) -> 88313.693 | E7: =sum('ACTUAL OPEX (JAN-JUN)'!H8:M8) -> 50556 | F7: =sum('ESTIMATED OPEX'!H8:M8) -> 36000 | G7: =B7-(C7+D7+E7+F7) -> 178248.14
A8: SM Rosales | B8: ='ACTUAL AND ESTIMATED REVENUE'!N9 -> 114321.06 | C8: =sum('ACTUAL OPEX (JAN-JUN)'!B9:G9) -> 17735.9 | D8: =sum('ESTIMATED OPEX'!B9:G9) -> 22078.423 | E8: =sum('ACTUAL OPEX (JAN-JUN)'!H9:M9) -> 25842.08 | F8: =sum('ESTIMATED OPEX'!H9:M9) -> 18000 | G8: =B8-(C8+D8+E8+F8) -> 30664.655
A9: Escala | B9: ='ACTUAL AND ESTIMATED REVENUE'!N10 -> 65072.067 | C9: =sum('ACTUAL OPEX (JAN-JUN)'!B10:G10) -> 7333.7 | D9: =sum('ESTIMATED OPEX'!B10:G10) -> 8831.3693 | E9: =sum('ACTUAL OPEX (JAN-JUN)'!H10:M10) -> 8800.44 | F9: =sum('ESTIMATED OPEX'!H10:M10) -> 10597.643 | G9: =B9-(C9+D9+E9+F9) -> 29508.914
A10: ADB | B10: ='ACTUAL AND ESTIMATED REVENUE'!N11 -> 549001.7 | C10: =sum('ACTUAL OPEX (JAN-JUN)'!B11:G11) -> 121768.24 | D10: =sum('ESTIMATED OPEX'!B11:G11) -> 97081.982 | E10: =sum('ACTUAL OPEX (JAN-JUN)'!H11:M11) -> 0 | F10: =sum('ESTIMATED OPEX'!H11:M11) -> 0 | G10: =B10-(C10+D10+E10+F10) -> 330151.48
A11: SM Sucat | B11: ='ACTUAL AND ESTIMATED REVENUE'!N12 -> 220784.23 | C11: =sum('ACTUAL OPEX (JAN-JUN)'!B12:G12) -> 0 | D11: =sum('ESTIMATED OPEX'!B12:G12) -> 88313.693 | E11: =sum('ACTUAL OPEX (JAN-JUN)'!H12:M12) -> 0 | F11: =sum('ESTIMATED OPEX'!H12:M12) -> 72000 | G11: =B11-(C11+D11+E11+F11) -> 60470.54
A12: World Trade Center | B12: ='ACTUAL AND ESTIMATED REVENUE'!N13 -> 58681.726 | C12: =sum('ACTUAL OPEX (JAN-JUN)'!B13:G13) -> 5254.1 | D12: =sum('ESTIMATED OPEX'!B13:G13) -> 12616.242 | E12: =sum('ACTUAL OPEX (JAN-JUN)'!H13:M13) -> 0 | F12: =sum('ESTIMATED OPEX'!H13:M13) -> 0 | G12: =B12-(C12+D12+E12+F12) -> 40811.384
A13: S Maison at Conrad | B13: ='ACTUAL AND ESTIMATED REVENUE'!N14 -> 350746.23 | C13: =sum('ACTUAL OPEX (JAN-JUN)'!B14:G14) -> 43425.1 | D13: =sum('ESTIMATED OPEX'!B14:G14) -> 88313.693 | E13: =sum('ACTUAL OPEX (JAN-JUN)'!H14:M14) -> 36000 | F13: =sum('ESTIMATED OPEX'!H14:M14) -> 72000 | G13: =B13-(C13+D13+E13+F13) -> 111007.44
... A16: SM Valenzuela | B16: ='ACTUAL AND ESTIMATED REVENUE'!N17 -> 220784.23 | C16: =sum('ACTUAL OPEX (JAN-JUN)'!B17:G17) -> 0 | D16: =sum('ESTIMATED OPEX'!B17:G17) -> 88313.693 | E16: =sum('ACTUAL OPEX (JAN-JUN)'!H17:M17) -> 36000 | F16: =sum('ESTIMATED OPEX'!H17:M17) -> 72000 | G16: =B16-(C16+D16+E16+F16) -> 24470.54
A21: CPO - JV
A22: S&R Libis | B22: ='ACTUAL AND ESTIMATED REVENUE'!N23 -> 309942.09 | C22: =sum('ACTUAL OPEX (JAN-JUN)'!B23:G23) -> 20877.5 | D22: =sum('ESTIMATED OPEX'!B23:G23) -> 82005.573 | E22: =sum('ACTUAL OPEX (JAN-JUN)'!H23:M23) -> 17301.297 | F22: =sum('ESTIMATED OPEX'!H23:M23) -> 68884.681 | G22: =B22-(C22+D22+E22+F22) -> 120873.04
A23: S&R Congressional | B23: ='ACTUAL AND ESTIMATED REVENUE'!N24 -> 282567.09 | C23: =sum('ACTUAL OPEX (JAN-JUN)'!B24:G24) -> 10843.9 | D23: =sum('ESTIMATED OPEX'!B24:G24) -> 82005.573 | E23: =sum('ACTUAL OPEX (JAN-JUN)'!H24:M24) -> 8903.355 | F23: =sum('ESTIMATED OPEX'!H24:M24) -> 68884.681 | G23: =B23-(C23+D23+E23+F23) -> 111929.58
A24: S&R New Manila | B24: ='ACTUAL AND ESTIMATED REVENUE'!N25 -> 311172.09 | C24: =sum('ACTUAL OPEX (JAN-JUN)'!B25:G25) -> 17047.2 | D24: =sum('ESTIMATED OPEX'!B25:G25) -> 82005.573 | E24: =sum('ACTUAL OPEX (JAN-JUN)'!H25:M25) -> 14175.387 | F24: =sum('ESTIMATED OPEX'!H25:M25) -> 68884.681 | G24: =B24-(C24+D24+E24+F24) -> 129059.25
A25: S&R Nuvali | B25: ='ACTUAL AND ESTIMATED REVENUE'!N26 -> 298158.09 | C25: =sum('ACTUAL OPEX (JAN-JUN)'!B26:G26) -> 19259.9 | D25: =sum('ESTIMATED OPEX'!B26:G26) -> 82005.573 | E25: =sum('ACTUAL OPEX (JAN-JUN)'!H26:M26) -> 16303.598 | F25: =sum('ESTIMATED OPEX'!H26:M26) -> 68884.681 | G25: =B25-(C25+D25+E25+F25) -> 111704.34
A27: SUB TOTAL: | B27: =SUM(B2:B25) -> 13362178 | C27: =SUM(C2:C25) -> 2845856.2 | D27: =SUM(D2:D25) -> 2770589.8 | E27: =SUM(E2:E25) -> 525460.43 | F27: =SUM(F2:F25) -> 929096.37 | G27: =SUM(G2:G25) -> 6291175.5
